{
  "couple_name": "Drew & Nicha",
  "start_date": "2022-03-01T09:00:00",
  "main_photo": "images/cover.jpg",
  "intro_message": "Happy 4th Anniversary",
  "purpose_message": "ขอบคุณที่จับมือกันมาถึงปีที่ 4 นะ เว็บนี้คือของขวัญที่ตั้งใจทำ ให้เธอ คนเดียวเลย ❤️",
  "memories": [
    {
      "year": "ปีที่ 1",
      "caption": "ไปหาเธอครั้งแรกดีใจมากเลยยย ❤️",
      "img": "images/year1d1.jpg"
    },
     {
      "year": "ปีที่ 1",
      "caption": "ไปเที่ยวด้วยกันครั้งแรก ❤️",
      "img": "images/year1d2.jpg"
    },
     {
      "year": "ปีที่ 1",
      "caption": "อาหารมื้อที่ 3 ในชีวิตคู่ ❤️",
      "img": "images/year1d3.mp4"
    },
     {
      "year": "ปีที่ 1",
      "caption": "รูปคู่ที่เค้าชอบที่สุดดดดในปีแรก ❤️",
      "img": "images/year1d4.jpg"
    },
    {
      "year": "ปีที่ 2",
      "caption": "ไปเจอแม่เค้าครั้งแรกกก ❤️",
      "img": "images/year2d2.jpg"
    },
     {
      "year": "ปีที่ 2",
      "caption": "มาขอนแก่นครั้งแรก ❤️",
      "img": "images/year2d1.jpg"
    },
       {
      "year": "ปีที่ 2",
      "caption": "อยู่กะแฟนแบบเท่ๆ ❤️",
      "img": "images/year2d3.mp4"
    },
       {
      "year": "ปีที่ 2",
      "caption": "ไปบ้านเค้าครั้งแรกกก ❤️",
      "img": "images/year2d4.mp4"
    },
     {
      "year": "ปีที่ 3",
      "caption": "มาหาเค้าครั้งที่สอง ❤️",
      "img": "images/year3d1.mp4"
    },
     {
      "year": "ปีที่ 3",
      "caption": "ไปบ้านเค้าครั้งที่สอง ❤️",
      "img": "images/year3d3.jpg"
    },
     {
      "year": "ปีที่ 3",
      "caption": "ไปเที่ยวภูผาม่านน ❤️",
      "img": "images/year3d3.mp4"
    },
     {
      "year": "ปีที่ 3",
      "caption": "ขับรถให้แฟนครั้งแรกกก ❤️",
      "img": "images/year3d2.mp4"
    },
      {
      "year": "ปีที่ 4",
      "caption": "ไปเที่ยวอ่างทองกับแฟนครั้งแรกกก ❤️",
      "img": "images/year4d1.mp4"
    },
      {
      "year": "ปีที่ 4",
      "caption": "มาหาเค้าครั้งที่ 3 ❤️",
      "img": "images/year4d2.mp4"
    },
      {
      "year": "ปีที่ 4",
      "caption": "ไปเที่ยวกับ ครอบครัวเค้า ❤️",
      "img": "images/year4d3.mp4"
    },
    {
      "year": "ปีที่ 4",
      "caption": "เคาน์ดาวน์ครั้งแรก ❤️",
      "img": "images/year4d4.mp4"
    }
  ]
}